farmhand/__init__.py
farmhand/farmhand.py
farmhand_util-0.1.0.dist-info/LICENSE
farmhand_util-0.1.0.dist-info/METADATA
farmhand_util-0.1.0.dist-info/WHEEL
farmhand_util-0.1.0.dist-info/entry_points.txt
farmhand_util-0.1.0.dist-info/top_level.txt
farmhand_util-0.1.0.dist-info/RECORD
